{"predictions":{"Nose":{"x":453,"y":645,"score":1},"LeftEye":{"x":486,"y":633,"score":1},"RightEye":{"x":438,"y":627,"score":1},"LeftEar":{"x":543,"y":690,"score":1},"RightEar":{"x":0,"y":0,"score":1},"LeftShoulder":{"x":570,"y":774,"score":1},"RightShoulder":{"x":375,"y":762,"score":1},"LeftElbow":{"x":684,"y":654,"score":1},"RightElbow":{"x":300,"y":594,"score":1},"LeftWrist":{"x":678,"y":492,"score":1},"RightWrist":{"x":315,"y":420,"score":1},"LeftHip":{"x":450,"y":1155,"score":1},"RightHip":{"x":324,"y":1125,"score":1},"LeftKnee":{"x":384,"y":1407,"score":1},"RightKnee":{"x":309,"y":1404,"score":1},"LeftAnkle":{"x":348,"y":1647,"score":1},"RightAnkle":{"x":336,"y":1623,"score":1}}}